{
  "App": {
    "Offers successfully restored": "Offerte ripristinate con successo",
    "Invalid offer": "Offerta non valida",
    "Offer successfully indexed": "Offerta indicizzata correttamente",
    "Error uploading offer": "Errore nel caricamento dell'offerta"
  },
  "nft": {
    "Unnamed NFT": "NFT senza nome",
    "No Preview Available": "Nessuna anteprima disponibile",
    "Sensitive Content": "Contenuto sensibile",
    "Click to always enable": "Fare clic per abilitare sempre",
    "Close Metadata": "Chiudi Metadata",
    "Inspect Metadata": "Analizza Metadata",
    "Blocked for violating community rules": "Bloccato per violazione delle regole della comunità",
    "Blocked": "Bloccato",
    "Anyone can create an NFT collection, make sure the creator is authentic": "Chiunque può creare una collezione NFT, assicurati che l'artista sia autentico",
    "Unknown Creator": "Artista Sconosciuto",
    "Creator DID claimed by {{name}} on {{via}}": "DID dell'artista richiesto da {{name}} attraverso {{via}}",
    "{{platform}} verified": "{{platform}} verificata",
    "{{platform}} unverified": "{{platform}} non verificata",
    "NFT Address": "Indirizzo NFT",
    "Royalty": "Diritti d'autore",
    "NFT Creator": "Artista NFT",
    "Created at Height": "Creato all'altezza",
    "Data URIs": "Data URIs",
    "Data Hash": "Data Hash",
    "Metadata URIs": "Metadata URIs",
    "Metadata Hash": "Metadata Hash",
    "License URIs": "License URIs",
    "License Hash": "License Hash",
    "NFT Markets": "Lista delle collezioni NFT sul mercato",
    "Newcomers": "Nuovi arrivi"
  },
  "common": {
    "CLIPPED": "COPIATO",
    "Search Tokens, NFTs or enter Address": "Trova i Tokens,gli NFTs o inserisci l'indirizzo",
    "You Offer": "La tua offerta",
    "Tokens (CATs)": "Tokens (CATs)",
    "Your NFTs": "I tuoi NFT",
    "You Request": "La tua richiesta",
    "Assets": "Risorse",
    "Contributors": "Team & Collaboratori",
    "Dark Mode": "Scuro",
    "Light Mode": "Chiaro",
    "Trade History": "Lista degli scambi avvenuti",
    "Report NFT": "Segnala NFT",
    "Show on MintGarden": "Mostra su MintGarden",
    "Show on Spacescan": "Mostra su Spacescan",
    "Accept in Wallet": "Accetta nel Portafogli",
    "Loading": "Caricamento in corso ...",
    "Price": "Prezzo",
    "Status": "Stato",
    "Requested": "Richiesto",
    "Offered": "Offerto",
    "loading": "Caricamento in corso",
    "{{count}} more_one": "Un offerta alternativa",
    "{{count}} more_many": "{{count}} offerte alternative",
    "{{count}} more_other": "{{count}} offerte alternative",
    "Inspect": "Vedi dettagli",
    "No Results": "Nessun risultato",
    "Current Price": "Prezzo Corrente",
    "New": "Nuovo",
    "Add to Wallet": "Aggiungi al portafogli",
    "Trade": "Compravendite",
    "Description": "Descrizione",
    "Daily Volume": "Volume giornaliero",
    "Website": "Sito Web",
    "Friends": "Amici",
    "Transaction Fees": "Costo di commissione",
    "Mempool Transaction ID": "ID di transazione nella Mempool",
    "Uploading": "Caricamento in corso...",
    "Currently Offered": "Offerte Correnti",
    "Weekly Volume": "Volume settimanale",
    "Monthly Volume": "Volume mensile",
    "Yearly Volume": "Volume annuale",
    "Rank by": "Ordinati per",
    "Daily Trades": "Vendite giornaliere",
    "Weekly Trades": "Vendite settimanali",
    "Monthly Trades": "Vendite mensili",
    "Yearly Trades": "Vendite annuali",
    "Suspicious trading activity (inflated volume)": "Attività sospetta (Volume elevato)",
    "NFTs for sale": "NFT in vendita",
    "Any Asset": "Ogni Asset",
    "Showing Newest": "Mostra recenti",
    "NFT Collection": "Collezione NFT",
    "Classic Chart": "Diagramma Classico",
    "Everything": "Tutto",
    "NFT Collections": "Collezioni NFT",
    "Select Reason": "Seleziona un motivo",
    "All Markets": "Tutti i mercati",
    "Date": "Data",
    "Actions": "Azioni",
    "Hide": "Nascondi"
  },
  "confirmTransactionModal": {
    "Confirm Transaction": "Conferma la transazione",
    "You Pay": "Paghi",
    "You Receive": "Ricevi",
    "Waiting for confirmation in your wallet": "In attesa di conferma dal Portafogli"
  },
  "Connect Wallet": "Connetti il tuo wallet",
  "header": {
    "Connect Wallet": "Connetti il Portafogli",
    "Markets": "Mercati",
    "NFT": "NFT",
    "Trade": "Compravendite",
    "Recent Trades": "Vendite Recenti",
    "FAQ": "FAQ",
    "bannerMessageLiquidityRewards": "Ora con <b>Liquidity Rewards</b>! Ottieni <b>dexie bucks</b> utilizzando le offerte fuse automaticamente",
    "Get USDS": "Ottieni USDS",
    "Your Offers": "Le tue offerte"
  },
  "connectModal": {
    "Not Installed": "Non installato",
    "To set up WalletConnect with the Chia Desktop Wallet, click the Code below to copy the connection link": "Per attivare il WalletConnect con il tuo Portafogli Desktop, Clicca il codice sotto per copiare il link di connessione",
    "Copy WalletConnect Link": "Copia il link di connessione WalletConnect",
    "Cancel WalletConnect": "Cancella WalletConnect",
    "Add with WalletConnect": "Aggiungi con WalletConnect",
    "Connect": "Connetti",
    "Connected": "Connesso",
    "Disconnected": "Disconnesso",
    "Remove": "Rimuovi",
    "Disconnect": "Disconnetti"
  },
  "createOffer": {
    "Please wait": "Cortesemente attendi...",
    "Create Offer with Goby": "Crea un offerta con Goby"
  },
  "footer": {
    "Public API": "Public API",
    "Help translate": "Help translate",
    "Blocks are fully utilized, recommended transaction fee {{fee}} {{xch}}": "I blocchi sono sovraccarichi di transazioni in attesa, si raccomanda una commissione minima di {{fee}} {{xch}}",
    "Status": "Stato",
    "synced": "Sincronizzato",
    "disconnected": "Disconnesso",
    "connecting": "Connessione in corso:",
    "More": "Di più"
  },
  "offersTable": {
    "Accept": "Accetta",
    "Download Offer File": "Scarica il file di offerta",
    "Copy Offer File": "Copia il file di offerta",
    "No Offers Found": "Nessun offerta trovata",
    "{{count}} Muted Assets_one": "Un asset nascosto",
    "{{count}} Muted Assets_many": "{{count}} asset nascosti",
    "{{count}} Muted Assets_other": "{{count}} asset nascosti",
    "Combine Offers": "Unisci offerte",
    "Collapse NFTs": "Comprimi NFT",
    "Expand NFTs": "Espandi NFT",
    "You Pay": "Pagherai",
    "You Receive": "Riceverai",
    "offersCount_one": "<0>{{formattedCount}}</0> Offerta",
    "offersCount_many": "<0>{{formattedCount}}</0> Offerte",
    "offersCount_other": "<0>{{formattedCount}}</0> Offerte",
    "Legacy offer, combination not supported": "Offerta Legacy, fusione non supportata",
    "This offer contains overlapping inputs or outputs and can not be added": "Questa offerta contiene input o output sovrapposti e non può essere aggiunta",
    "Last": "Ultima",
    "Best Price": "Miglior Prezzo",
    "New": "Nuova",
    "Blocks ago_one": "<0>{{formattedCount}}</0> Blocco fa",
    "Blocks ago_many": "<0>{{formattedCount}}</0> Blocchi fa",
    "Blocks ago_other": "<0>{{formattedCount}}</0> Blocchi fa"
  },
  "ribbon": {
    "Yours": "Le tue"
  },
  "ozoneModal": {
    "Scan QR Code with Ozone Wallet to accept": "Scansione il QR Code con il portafogli Ozone per accettare",
    "Try Ozone Wallet": "Prova il portafogli Ozone",
    "Ozone Wallet is designed for transactions with XCH and CATs in a reliable and secure way": "Il portafogli Ozone è studiato per effettuare transazioni con XCH e CATs in modo sicuro e affidabile"
  },
  "inspect": {
    "dexie link": "Link a Dexie",
    "Loading": "Caricamento di corso...",
    "offer not found": "Offerta non trovata",
    "Requested": "Richiesto",
    "Offered": "Offerto",
    "Step {{count}}_one": "Passo {{count}}",
    "Step {{count}}_many": "Passo {{count}}",
    "Step {{count}}_other": "Passo {{count}}",
    "Download Offer": "Scarica Offerta",
    "Offer file copied": "File di offerta copiato",
    "Copy to Clipboard": "Copia sul clipboard",
    "Status": "Stato",
    "Offer ID (Hash)": "ID dell'offerta (Hash)",
    "Date Collected": "Data di inserimento",
    "Date Expiry": "Data di Scadenza",
    "Date Pending": "Data di accettazione",
    "Date Closed": "Date di completamento transazione",
    "Confirmed at Height": "Confermata all'altezza",
    "Message Address": "Indirizzo del messaggio",
    "Escrow Address": "Indirizzo di deposito a garanzia",
    "Raw Offer File": "Inserisci qui il contenuto testuale del tuo file di offerta",
    "Cross-Chain": "Cross-Chain",
    "Your Offer has been submitted, add it to Your Offers to bookmark it": "La tua offerta è stata sottomessa, inseriscila nelle Tue Offerte per aggiungerla ai segnalibri",
    "Add to Your Offers": "Carica le tue offerte",
    "Go to Trade": "Vai alle compravendite",
    "Completed before collection date": "Completata prima della data di pubblicazione",
    "Cancelled before collection date": "Completata prima della data di pubblicazione",
    "Trade ID": "Trade ID",
    "Confirmed at Block": "Confermato al blocco",
    "Number of confirmations": "Numero di conferma",
    "attached": "allegato",
    "Cancelled Maker Inputs": "Maker Inputs Cancellati",
    "Maker Inputs": "Maker Inputs",
    "Taker Inputs": "Taker Inputs",
    "Offer successfully executed": "Offerta effettuata con successo",
    "Inputs may be larger than outputs, any excess amount was returned as change": "Gli input possono essere maggiori degli output, qualsiasi importo in eccesso è stato restituito come resto",
    "Larger outputs indicate that this offer was combined with other offers": "Output più grandi indicano che questa offerta è stata combinata con altre offerte",
    "Pending Maker Outputs": "In attesa di Maker Outputs",
    "Cancelled Maker Outputs": "Maker Outputs cancellati",
    "Maker Outputs": "Maker Outputs",
    "Taker Outputs": "Taker Outputs",
    "Pending Royalties": "In attesa dei diritti d'autore",
    "Cancelled Royalties": "Diritti d'autore cancellati",
    "Royalties": "Diritti d'autore",
    "Current Bid": "Offerta corrente",
    "Make Bid": "Fai un offerta",
    "Requested price is too high? The seller might accept your bid!": "Il prezzo richiesto è troppo alto! Il venditore potrebbe accettare la tua offerta!",
    "{{count}} offers_one": "un offerta",
    "{{count}} offers_many": "{{count}} offerte",
    "{{count}} offers_other": "{{count}} offerte",
    "Bid with Goby": "Offri con Goby",
    "Upload Offer": "Carica offerte",
    "Create a new offer which requests this NFT": "Crea una nuova offerta che richiede questo NFT",
    "Unknown": "Sconosciuto"
  },
  "chart": {
    "Day": "Giorno",
    "Week": "Settimana",
    "Month": "Mese",
    "3 Month": "3 Mesi",
    "Year": "Anno",
    "Linear": "Lineare",
    "Log": "Logaritmico",
    "activeOffers": "Offerte attive",
    "lastPrice": "Ultimo prezzo",
    "Collapse": "Riduci",
    "Expand": "Allarga",
    "No data for this chart": "Nessun dato per questo diagramma",
    "Still collecting data for this chart": "Raccolta dati per questo diagramma in corso"
  },
  "status": {
    "active": "Attivo",
    "pending": "In corso",
    "cancelling": "In annullamento",
    "cancelled": "Annullato",
    "completed": "Completato",
    "unknown": "Sconosciuto",
    "expired": "Scaduta"
  },
  "toast": {
    "gobyError4001": "Cortesemente termina la configuarazione di Goby",
    "gobyError4900": "Goby non è connesso",
    "Request rejected": "Richiesta rigettata",
    "Offer rejected": "Offerta rigettata",
    "Please reconnect your wallet to perform this action": "Cortesemente connetti nuovamente il portafogli per eseguire questa azione",
    "Offer accepted": "Offerta Accettata",
    "Asset added": "Asset aggiunto"
  },
  "signMessage": {
    "Address not found in {{walletName}}": "Indirizzo non trovato in {{walletName}}",
    "Message signed": "Messaggio firmato"
  },
  "This feature is not supported by {{wallet}}": "Quasta funzionalità non è supportata da {{wallet}}",
  "signAddress": {
    "No key for this address": "Nessuna chiave per questo indirizzo",
    "Invalid address": "Indirizzo non valido"
  },
  "Assets": {
    "Powered by Tail Database": "Fonte Tail Database",
    "Search {{count}} assets_one": "Trova Asset Attivo",
    "Search {{count}} assets_many": "Trova {{count}} Asset Attivi",
    "Search {{count}} assets_other": "Trova {{count}} Asset Attivi",
    "Show All": "Mostra tutti",
    "Show Muted": "Mostra nascosti",
    "No Muted Assets": "Nessun asset nascosto",
    "Asset Not Found": "Asset non trovato",
    "Mute assets to prevent them from showing up for you": "Nascondi gli asset per evitare che questi ti vengano mostrati",
    "Unmute": "Rendi visibile",
    "Mute": "Nascondi",
    "Code": "Codice Moneta",
    "Asset ID": "Asset ID",
    "Current Average Price": "Prezzo medio corrente",
    "{{code}} Liquidity": "Liquidità in {{code}}"
  },
  "claimHistory": {
    "Claimed Rewards History": "Storia delle ricompense rivendicate",
    "Learn more about the Liquidity Incentive Program": "Scopri di piu circa il programma degli incentivi di liquidità",
    "Total Rewards Claimed": "Ricompense totali rivendicate",
    "Within Last Month Claimed": "Rivendicato entro il mese scorso",
    "Outstanding Claims": "reclami in sospeso",
    "Daily Reward Rate": "Tasso di ricompensa giornaliero",
    "Claimed Reward": "Ricompensa rivendicata",
    "Claimed By": "Rivendicato da",
    "Date": "Data",
    "Queued": "In coda",
    "Sent": "Inviata",
    "Offer": "Offerta",
    "Distribution Coin": "Moneta di distribuzione",
    "Public Key": "Public Key",
    "Signature": "Signature"
  },
  "contributors": {
    "Core Contributor": "Collaboratori principali",
    "Community Manager": "Community Manager",
    "Advisor/Strategy": "Consulenti/Strategia",
    "Data Cruncher": "Data Cruncher",
    "Translator": "Traduttore",
    "DBX Holders": "Possessori di DBX",
    "The Community": "Community",
    "Web3 Wallet": "Web3 Wallet",
    "Explore NFTs": "Scopri gli NFT",
    "Add or Query TAILs": "Aggiungi o Ricerca TAIL",
    "dexie would like to thank its awesome contributors and friends, without them dexie wouldn't be what it is today": "Dexie vorrebbe ringraziare i suoi fantastici collaboratori e amici, senza di loro Dexie non sarebbe quello che è oggi!"
  },
  "uploadOffer": {
    "offerFileSuccessfullyIndexed": "File di offerta indicizzato con successo",
    "Submit Offer": "Presenta offerta",
    "Paste from Clipboard": "Incolla dal Clipboard",
    "Offer creator address does not exist in connected wallet": "L'indirizzo del creatore dell'offerta non esiste nel portafoglio connesso",
    "Rewards": "Ricompense",
    "Upload Offer Files": "Carica file di offerta",
    "Create with Goby": "Crea con Goby",
    "Paste Offer": "Incolla offerta",
    "Bulk Upload": "Caricamento Massivo",
    "API": "API",
    "Backup / Restore": "Backup / Restore",
    "#dragHint": "Trascina qui il tuo file di offerta",
    "Raw Offer here": "Inserisci qui il contenuto testuale del tuo file di offerta",
    "No Offer entered": "Nessuna offerta inserita",
    "Upload many offers in a ZIP file, dexie will internally queue and publish them without overloading the nodes": "Carica più offerte in un file ZIP, dexie metterà internamente in coda e pubblicherà senza sovraccaricare i nodi",
    "Successfully queued {{count}} offers for submission_one": "un offerta sottomessa alla coda con successo.",
    "Successfully queued {{count}} offers for submission_many": "{{count}} offerte sottomesse alla coda con successo.",
    "Successfully queued {{count}} offers for submission_other": "{{count}} offerte sottomesse alla coda con successo.",
    "Select and Upload ZIP file": "Seleziona e carica il file ZIP",
    "Offers from Bulk Upload won't show up in Your Added Offers": "Le offerte dal caricamento massivo non verranno visualizzate nelle tue offerte aggiunte.",
    "See the API documentation for more information and examples": "Guarda la documentazione delle API per maggiori informazioni ed esempi",
    "Your added offers are privately stored in your Browser, make a backup before clearing your Local Storage": "Le tue offerte aggiunte vengono archiviate privatamente nel tuo browser, fai un backup prima di cancellare la tua memoria locale.",
    "Backup Your Offers": "Fai backup delle tue offerte",
    "Restore Your Offers": "Ripristina le tue offerte",
    "Duplicate offers will be merged": "Le offerte doppie saranno fuse.",
    "Your Added Offers": "Le tue offerte aggiunte",
    "Your added offers appear here": "Le tue offerte aggiunte appaiono qui",
    "No matching offers": "Offerte senza corrispondenza",
    "Offers close to the market price can receive rewards (click for more)": "Le offerte vicine al prezzo di mercato possono ricevere premi (fare clic per ulteriori informazioni)",
    "Liquidity Rewards": "Liquidity Rewards",
    "Reward Claimed": "Ricompense rivendicate",
    "Claim": "Ottieni",
    "Eligible": "Idonea"
  },
  "faq": {
    "question1": "Che cosa è Dexie?",
    "answer1": "<p class='my-5'>Dexie è un Exchange peer-to-peer per i file delle offerte Chia. I file delle offerte sono completamente decentralizzati e affidabili.</p><p class='my-5'>Dexie non detiene in custodia alcuna moneta, queste rimangono sempre nel portafogli dell'utente fino a quando l'offerta non viene accettata, a quel punto le risorse vengono trasferite in modo sicuro tra il venditore e l'acquirente all'interno di un'unica transazione sulla blockchain senza alcun intermediario.</p><p class='my-5'>Scopri i vantaggi dei file offerta sul sito ufficiale della <a class='text-nice underline' href='https://chialisp.com/offers' target='_blank' rel='noreferrer'>documentazione di Chia Network</a>.</p>",
    "question2": "Supporto o domande?",
    "answer2": "<p class='my-5'>Contattaci su Twitter a <a class='text-nice underline' href='https://twitter.com/dexie_space' target='_blank' rel='noreferrer'>@dexie_space</a> o raggiungici su <a class='text-nice underline' href='https://discord.gg/3xUrkAxUmd' target='_blank' rel='noreferrer'>discord channel</a>, siamo felici di poterti aiutare.</p>"
  },
  "markets": {
    "{{market}} subheading": "Tutti gli asset conosciuti con almeno un {{market}} di liquidità in vendita",
    "{{market}} heading": "Mercati in {{market}}",
    "Price Depth": "Profondità del prezzo",
    "Rank": "Classifica",
    "Asset": "Asset",
    "#buyPriceHint{{depth}}": "Il prezzo unitario per l'acquisto di {{depth}} {{market}} \n e quanto otterrebbe ogni {{market}}.",
    "Buy Price": "Prezzo di acquisto",
    "#sellPriceHint{{depth}}": "Il prezzo unitario per l'acquisto di {{depth}} {{market}} \n e quanto costerebbe ogni {{market}}.",
    "Sell Price": "Prezzo di vendita",
    "Provide liquidity to earn DBX rewards": "Aggiungi liquidità per ottenere DBX",
    "Incentives": "Incentivi",
    "Buy": "Compra",
    "Sell": "Vendi",
    "no liquidity": "Nessuna liquidità",
    "Learn more about our NFT Verification Labels": "Scopri di più sulle nostre etichette di verifica NFT",
    "Collection": "Collezione",
    "The current lowest price of an NFT": "Prezzo corrente più basso di un NFT",
    "Buy Price (Floor)": "Prezzo di acquisto",
    "The highest price someone is bidding for an NFT": "Il più alto prezzo che qualcuno sta offrendo per un NFT",
    "Highest Bid": "Offerta più alta",
    "Floor 24h": "Floor 24h",
    "Toggle collections with suspicious trading activity": "Attiva/disattiva le collezioni con attività di trading sospette",
    "no {{xch}} offers": "Nessun {{xch}} offerto"
  },
  "notFound": {
    "404 Error": "Error 404",
    "Page not found": "Pagina non trovata",
    "Sorry, we couldn't find the page you're looking for": "Mi spiace, non troviamo la pagina che stai cercando",
    "Go back home": "Torna alla Home"
  },
  "offers": {
    "Sell": "Vendi",
    "Buy": "Compra"
  },
  "autoCombine": {
    "Combining Offers": "Fusione offerte in corso",
    "Combined Offer": "Offerta fusa",
    "Auto-Combined": "Fusione automatica",
    "Bonus": "Regalo",
    "{{fee}}% Combination Fee included ({{count}} Coin-Spends)_one": "Commissione di fusione al {{fee}}% inclusa. (Una moneta spesa)",
    "{{fee}}% Combination Fee included ({{count}} Coin-Spends)_many": "Commissione di fusione al {{fee}}% inclusa. ({{count}} monete spese)",
    "{{fee}}% Combination Fee included ({{count}} Coin-Spends)_other": "Commissione di fusione al {{fee}}% inclusa. ({{count}} monete spese)",
    "Fee": "Commissione",
    "No offers to auto-combine, try a larger amount or choose the best offer from below": "Nessuna offerta da fondere, prova un importo più alto oppure scegli la migliore offerta qui sotto",
    "High Slippage": "Slittamento Elevato",
    "Best Combined": "Fusione Migliore"
  },
  "report": {
    "Report Content": "Fai delle segnalazioni",
    "Use this form to report NFTs or Tokens for rule violations": "Usa questo per segnalare NFT o Token che violano le regole.",
    "Every report becomes a public pull request in the Community Blocklist repository, where it will be reviewed by a maintainer": "Tutte le segnalazioni diventano una pubblica segnazione sull'archivio  <a class='text-nice underline' href='https://github.com/dexie-space/blocklist' target='_blank' rel='noopener'>Community Blocklist</a>, dove sara analizzata da un nostro esperto",
    "NFT": "NFT",
    "CAT reporting is not available right now": "Le segnalazioni sui CAT non sono attive in questo momento",
    "Token (CAT)": "Token (CAT)",
    "Impersonation": "Furto di identità",
    "Spam": "Spam",
    "Illegal Content": "Contenuto illecito",
    "Other": "Altro",
    "Please enter as much additional information as possible that can be used to review this report, eg links to the original collection in case of an impersonation report (all notes are public)": "Inserisci quante più informazioni aggiuntive possibili che possono essere utilizzate per esaminare questa segnalazione, ad esempio collegamenti alla raccolta originale in caso di segnalazione di furto d'identità (tutte le note sono pubbliche)",
    "Thank you, a new report has been generated": "Grazie, una nuova segnalazione è stata aggiunta",
    "Report {{id}}": "Segnalazione {{id}}",
    "Generating Report": "Generazione segnalazione in corso ...",
    "Submit Report": "Invia segnalazione"
  },
  "trades": {
    "Recommended Transaction Fee": "Commissione di transazione consigliata",
    "Tx Fee": "Commissione di transazione",
    "mempoolExplanation": "Le transazioni sono in attesa di essere incluse in un blocco",
    "mempoolSize": "Mempool",
    "no filters selected": "Nessun filtro selezionato",
    "Toggle suspicious trades (wash trading, spam)": "Attività sospette (wash trading, spam)",
    "Transaction Fee (higher fee = higher priority)": "Commissione di transazione (Commissione alta=priorità alta)",
    "Low Transaction Fee (low priority) {{fee}}": "Commissione di transazione bassa (bassa priorità) {{fee}}",
    "Low Fee": "Commissione bassa"
  }
}
